pyhasse.spyout-0.3.1-py3.7-nspkg.pth
pyhasse/spyout/__init__.py
pyhasse/spyout/calc.py
pyhasse.spyout-0.3.1.dist-info/AUTHORS.rst
pyhasse.spyout-0.3.1.dist-info/LICENSE
pyhasse.spyout-0.3.1.dist-info/METADATA
pyhasse.spyout-0.3.1.dist-info/WHEEL
pyhasse.spyout-0.3.1.dist-info/namespace_packages.txt
pyhasse.spyout-0.3.1.dist-info/top_level.txt
pyhasse.spyout-0.3.1.dist-info/RECORD
