Metadata-Version: 2.1
Name: pyhasse.spyout
Version: 0.3.1
Summary: pyhasse.spyout: First inspection of data-driven partially ordered sets.
Home-page: https://pyhasse.org
Author: Rainer Bruggemann
Author-email: rainer.bruggemann@pyhasse.org
License: MIT license
Download-URL: https://pyhasse.org
Keywords: spyout
Platform: UNKNOWN
Classifier: Development Status :: 2 - Pre-Alpha
Classifier: Intended Audience :: Developers
Classifier: Intended Audience :: Science/Research
Classifier: Topic :: Scientific/Engineering :: Mathematics
Classifier: License :: OSI Approved :: MIT License
Classifier: Natural Language :: English
Classifier: Programming Language :: Python :: 3.9
Requires-Dist: setuptools
Requires-Dist: pyhasse.core
